Metadata-Version: 1.0
Name: gb-dists
Version: 0.1
Summary: Gaussian and Binomial distributions
Home-page: UNKNOWN
Author: Yakup Akkaya
Author-email: UNKNOWN
License: UNKNOWN
Platform: UNKNOWN
